jupyterlab_etiq/__init__.py
jupyterlab_etiq/_version.py
jupyterlab_etiq-2.2.3.data/data/share/jupyter/labextensions/jupyterlab-etiq/package.json
jupyterlab_etiq-2.2.3.data/data/share/jupyter/labextensions/jupyterlab-etiq/schemas/jupyterlab-etiq/package.json.orig
jupyterlab_etiq-2.2.3.data/data/share/jupyter/labextensions/jupyterlab-etiq/schemas/jupyterlab-etiq/plugin.json
jupyterlab_etiq-2.2.3.data/data/share/jupyter/labextensions/jupyterlab-etiq/static/329.719b2deb4b106ca70678.js
jupyterlab_etiq-2.2.3.data/data/share/jupyter/labextensions/jupyterlab-etiq/static/494.d8c06f960b80640f01ee.js
jupyterlab_etiq-2.2.3.data/data/share/jupyter/labextensions/jupyterlab-etiq/static/494.d8c06f960b80640f01ee.js.LICENSE.txt
jupyterlab_etiq-2.2.3.data/data/share/jupyter/labextensions/jupyterlab-etiq/static/635.de03386b752ea3a7c4a9.js
jupyterlab_etiq-2.2.3.data/data/share/jupyter/labextensions/jupyterlab-etiq/static/635.de03386b752ea3a7c4a9.js.LICENSE.txt
jupyterlab_etiq-2.2.3.data/data/share/jupyter/labextensions/jupyterlab-etiq/static/665.ae37e324d0ec64cf6126.js
jupyterlab_etiq-2.2.3.data/data/share/jupyter/labextensions/jupyterlab-etiq/static/734.a4f59571da6156657c5a.js
jupyterlab_etiq-2.2.3.data/data/share/jupyter/labextensions/jupyterlab-etiq/static/remoteEntry.b2f3a881f2cbf8464848.js
jupyterlab_etiq-2.2.3.data/data/share/jupyter/labextensions/jupyterlab-etiq/static/style.js
jupyterlab_etiq-2.2.3.data/data/share/jupyter/labextensions/jupyterlab-etiq/static/third-party-licenses.json
jupyterlab_etiq-2.2.3.data/data/share/jupyter/labextensions/jupyterlab-etiq/install.json
jupyterlab_etiq-2.2.3.dist-info/METADATA
jupyterlab_etiq-2.2.3.dist-info/WHEEL
jupyterlab_etiq-2.2.3.dist-info/licenses/LICENSE
jupyterlab_etiq-2.2.3.dist-info/RECORD
